bedrock_models/__init__.py
bedrock_models/bedrock_model_ids.py
bedrock_models/bedrock_model_ids.pyi
bedrock_models/bedrock_models.json
bedrock_models/utils.py
bedrock_models-0.1.20.dist-info/METADATA
bedrock_models-0.1.20.dist-info/WHEEL
bedrock_models-0.1.20.dist-info/licenses/LICENSE
bedrock_models-0.1.20.dist-info/RECORD
