Metadata-Version: 2.4
Name: bedrock-models
Version: 0.1.20
Summary: A library that provides Bedrock models id
License: MIT-0
License-File: LICENSE
Author: Massimiliano Angelino
Author-email: massi.ang@gmail.com
Requires-Python: >=3.10,<4.0
Classifier: License :: OSI Approved
Classifier: Programming Language :: Python :: 3
Classifier: Programming Language :: Python :: 3.10
Classifier: Programming Language :: Python :: 3.11
Classifier: Programming Language :: Python :: 3.12
Classifier: Programming Language :: Python :: 3.13
Classifier: Programming Language :: Python :: 3.14
Requires-Dist: typing-extensions (>=4.15.0,<5.0.0)
